{"version":9,"M.VERSTAPPEN":{"updated":0,"state":0,"lap":33,"lap_time":82.316,"position":2,"gap":7.965,"interval":7.965,"pits":1,"best_time":0,"driver_number":1,"speed":264,"gear":7,"gear_switches":1263,"drs":0,"lap_pos":0.743,"engine_rpm":10477,"tyre_compound":[[9,28],[10,8]],"start_pos":1,"points":416,"speed_traps":[287,0,0,325],"max_speed_traps":[287,287,245,329],"s1":29.147,"s2":0,"s3":0,"best_times":[29.107,31.822,21.135,82.166]},"G.RUSSELL":{"updated":0,"state":0,"lap":33,"lap_time":83.269,"position":1,"gap":0,"interval":0,"pits":0,"best_time":0,"driver_number":63,"speed":168,"gear":4,"gear_switches":1646,"drs":0,"lap_pos":0.8616,"engine_rpm":10447,"tyre_compound":[[10,33]],"start_pos":2,"points":231,"speed_traps":[285,280,0,324],"max_speed_traps":[291,280,244,325],"s1":29.526,"s2":32.328,"s3":0,"best_times":[29.304,32.17,21.344,82.934]},"L.HAMILTON":{"updated":0,"state":0,"lap":33,"lap_time":82.419,"position":3,"gap":14.818,"interval":6.761,"pits":1,"best_time":1,"driver_number":44,"speed":227,"gear":6,"gear_switches":1558,"drs":0,"lap_pos":0.6509,"engine_rpm":10503,"tyre_compound":[[10,29],[11,4]],"start_pos":3,"points":216,"speed_traps":[286,0,0,323],"max_speed_traps":[289,279,245,326],"s1":29.121,"s2":0,"s3":0,"best_times":[29.121,31.798,21.124,82.062]},"S.PEREZ":{"updated":0,"state":0,"lap":33,"lap_time":82.437,"position":4,"gap":16.687,"interval":1.839,"pits":1,"best_time":0,"driver_number":11,"speed":215,"gear":5,"gear_switches":1207,"drs":0,"lap_pos":0.625,"engine_rpm":11171,"tyre_compound":[[9,26],[10,10]],"start_pos":4,"points":280,"speed_traps":[280,0,0,332],"max_speed_traps":[294,289,247,350],"s1":28.958,"s2":0,"s3":0,"best_times":[28.421,31.68,21.248,81.775]},"C.SAINZ":{"updated":0,"state":0,"lap":33,"lap_time":83.096,"position":7,"gap":43.071,"interval":4.819,"pits":1,"best_time":0,"driver_number":55,"speed":249,"gear":6,"gear_switches":1616,"drs":2,"lap_pos":0.3321,"engine_rpm":11598,"tyre_compound":[[9,32],[10,4]],"start_pos":5,"points":212,"speed_traps":[286,277,243,335],"max_speed_traps":[292,282,245,335],"s1":29.254,"s2":32.317,"s3":21.525,"best_times":[28.839,32.08,21.28,82.199]},"V.BOTTAS":{"updated":0,"state":0,"lap":33,"lap_time":84.146,"position":6,"gap":38.235,"interval":2.925,"pits":0,"best_time":0,"driver_number":77,"speed":215,"gear":7,"gear_switches":1389,"drs":0,"lap_pos":0.4097,"engine_rpm":9384,"tyre_compound":[[10,33]],"start_pos":6,"points":47,"speed_traps":[288,0,0,322],"max_speed_traps":[290,284,244,347],"s1":29.678,"s2":0,"s3":0,"best_times":[29.246,32.661,21.696,83.933]},"C.LECLERC":{"updated":0,"state":0,"lap":33,"lap_time":83.106,"position":8,"gap":46.945,"interval":3.85,"pits":1,"best_time":0,"driver_number":16,"speed":124,"gear":3,"gear_switches":1591,"drs":0,"lap_pos":0.2904,"engine_rpm":9670,"tyre_compound":[[9,30],[10,5]],"start_pos":7,"points":275,"speed_traps":[290,277,243,322],"max_speed_traps":[299,283,243,342],"s1":29.212,"s2":32.475,"s3":21.419,"best_times":[28.66,32.309,21.364,82.699]},"L.NORRIS":{"updated":0,"state":0,"lap":32,"lap_time":104.158,"position":15,"gap":69.365,"interval":2.891,"pits":1,"best_time":0,"driver_number":4,"speed":227,"gear":5,"gear_switches":1335,"drs":0,"lap_pos":0.9802,"engine_rpm":11484,"tyre_compound":[[10,31],[11,1]],"start_pos":8,"points":111,"speed_traps":[282,278,0,325],"max_speed_traps":[290,286,247,356],"s1":29.563,"s2":32.853,"s3":0,"best_times":[29.224,32.787,21.759,84.282]},"F.ALONSO":{"updated":0,"state":0,"lap":33,"lap_time":84.285,"position":5,"gap":35.292,"interval":18.33,"pits":0,"best_time":0,"driver_number":14,"speed":85,"gear":2,"gear_switches":1476,"drs":0,"lap_pos":0.4494,"engine_rpm":7164,"tyre_compound":[[10,33]],"start_pos":9,"points":71,"speed_traps":[292,0,0,324],"max_speed_traps":[293,277,243,328],"s1":29.609,"s2":0,"s3":0,"best_times":[29.576,32.542,21.646,83.876]},"E.OCON":{"updated":0,"state":3,"lap":33,"lap_time":87.662,"position":12,"gap":43.246,"interval":0,"pits":-22313,"best_time":0,"driver_number":31,"speed":165,"gear":3,"gear_switches":1443,"drs":0,"lap_pos":0.081,"engine_rpm":11510,"tyre_compound":[[10,33],[11,0]],"start_pos":10,"points":82,"speed_traps":[0,0,0,0],"max_speed_traps":[294,283,242,346],"s1":0,"s2":0,"s3":0,"best_times":[29.273,32.793,21.854,84.299]},"D.RICCIARDO":{"updated":0,"state":0,"lap":33,"lap_time":84.526,"position":9,"gap":52.526,"interval":5.341,"pits":0,"best_time":0,"driver_number":3,"speed":99,"gear":3,"gear_switches":1563,"drs":0,"lap_pos":0.2486,"engine_rpm":6854,"tyre_compound":[[10,33]],"start_pos":11,"points":35,"speed_traps":[284,279,244,327],"max_speed_traps":[287,286,245,350],"s1":29.604,"s2":33.005,"s3":21.917,"best_times":[29.169,32.976,21.652,84.321]},"G.ZHOU":{"updated":0,"state":0,"lap":33,"lap_time":84.639,"position":10,"gap":57.565,"interval":4.985,"pits":0,"best_time":0,"driver_number":24,"speed":319,"gear":8,"gear_switches":1340,"drs":0,"lap_pos":0.1685,"engine_rpm":11402,"tyre_compound":[[10,33]],"start_pos":12,"points":6,"speed_traps":[288,275,242,320],"max_speed_traps":[291,284,243,344],"s1":29.734,"s2":32.985,"s3":21.92,"best_times":[29.372,32.911,21.652,84.471]},"Y.TSUNODA":{"updated":0,"state":0,"lap":32,"lap_time":84.123,"position":16,"gap":71.162,"interval":1.797,"pits":1,"best_time":0,"driver_number":22,"speed":175,"gear":4,"gear_switches":1370,"drs":0,"lap_pos":0.9617,"engine_rpm":11410,"tyre_compound":[[9,29],[10,3]],"start_pos":13,"points":12,"speed_traps":[276,280,0,330],"max_speed_traps":[288,288,248,350],"s1":29.41,"s2":33.369,"s3":0,"best_times":[29.076,32.822,21.601,83.617]},"P.GASLY":{"updated":0,"state":0,"lap":33,"lap_time":85.061,"position":13,"gap":62.009,"interval":1.606,"pits":0,"best_time":0,"driver_number":10,"speed":317,"gear":8,"gear_switches":1362,"drs":0,"lap_pos":0.0916,"engine_rpm":11199,"tyre_compound":[[10,33]],"start_pos":14,"points":23,"speed_traps":[286,278,245,330],"max_speed_traps":[295,286,245,353],"s1":29.582,"s2":33.495,"s3":21.984,"best_times":[29.18,33.069,21.771,84.446]},"M.SCHUMACHER":{"updated":0,"state":0,"lap":32,"lap_time":86.121,"position":19,"gap":-1,"interval":12.488,"pits":1,"best_time":0,"driver_number":47,"speed":190,"gear":5,"gear_switches":1521,"drs":0,"lap_pos":0.7013,"engine_rpm":10519,"tyre_compound":[[9,29],[10,8]],"start_pos":15,"points":12,"speed_traps":[287,0,0,328],"max_speed_traps":[287,284,244,352],"s1":29.541,"s2":0,"s3":0,"best_times":[29.219,32.682,21.536,83.641]},"S.VETTEL":{"updated":0,"state":0,"lap":33,"lap_time":84.918,"position":11,"gap":60.46,"interval":2.895,"pits":0,"best_time":0,"driver_number":5,"speed":317,"gear":8,"gear_switches":1476,"drs":0,"lap_pos":0.1168,"engine_rpm":11683,"tyre_compound":[[9,33]],"start_pos":16,"points":36,"speed_traps":[284,277,242,325],"max_speed_traps":[293,285,242,347],"s1":29.85,"s2":33.127,"s3":21.941,"best_times":[29.408,32.968,21.829,84.607]},"A.ALBON":{"updated":0,"state":0,"lap":33,"lap_time":84.815,"position":14,"gap":66.519,"interval":4.448,"pits":0,"best_time":0,"driver_number":23,"speed":277,"gear":7,"gear_switches":1277,"drs":0,"lap_pos":0.02,"engine_rpm":11537,"tyre_compound":[[10,33]],"start_pos":17,"points":4,"speed_traps":[292,278,243,331],"max_speed_traps":[294,286,243,354],"s1":29.428,"s2":33.323,"s3":22.064,"best_times":[29.086,33.096,22.036,84.55]},"N.LATIFI":{"updated":0,"state":0,"lap":32,"lap_time":85.534,"position":20,"gap":-1,"interval":13.817,"pits":1,"best_time":0,"driver_number":6,"speed":160,"gear":3,"gear_switches":1343,"drs":0,"lap_pos":0.5243,"engine_rpm":11369,"tyre_compound":[[9,23],[11,9]],"start_pos":18,"points":2,"speed_traps":[286,0,0,329],"max_speed_traps":[287,287,244,356],"s1":29.546,"s2":0,"s3":0,"best_times":[29.307,33.253,21.986,84.982]},"K.MAGNUSSEN":{"updated":0,"state":0,"lap":32,"lap_time":85.048,"position":18,"gap":82.263,"interval":1.311,"pits":0,"best_time":0,"driver_number":20,"speed":107,"gear":2,"gear_switches":1286,"drs":0,"lap_pos":0.8755,"engine_rpm":9387,"tyre_compound":[[10,32]],"start_pos":19,"points":24,"speed_traps":[270,275,0,323],"max_speed_traps":[287,280,242,348],"s1":30.6,"s2":33.557,"s3":0,"best_times":[29.244,33.15,22.059,84.862]},"L.STROLL":{"updated":0,"state":0,"lap":32,"lap_time":84.457,"position":17,"gap":80.952,"interval":9.885,"pits":1,"best_time":1,"driver_number":18,"speed":73,"gear":2,"gear_switches":1428,"drs":0,"lap_pos":0.8901,"engine_rpm":5875,"tyre_compound":[[10,18],[9,15]],"start_pos":20,"points":13,"speed_traps":[295,275,0,345],"max_speed_traps":[295,284,243,348],"s1":29.294,"s2":32.952,"s3":0,"best_times":[29.294,32.735,21.655,84.116]}}