{"version":9,"E.OCON":{"updated":0,"state":0,"lap":1,"lap_time":0,"position":14,"gap":19.441,"interval":0.323,"pits":0,"best_time":3,"driver_number":31,"speed":124,"gear":3,"gear_switches":171,"drs":0,"lap_pos":0.8932,"engine_rpm":8212,"tyre_compound":[[5,1]],"start_pos":14,"points":4,"speed_traps":[240,221,0,298],"max_speed_traps":[240,221,240,298],"s1":34.023,"s2":35.365,"s3":0,"best_times":[34.023,35.365,27.942,0]},"L.HAMILTON":{"updated":0,"state":0,"lap":2,"lap_time":91.458,"position":1,"gap":0,"interval":0,"pits":0,"best_time":136,"driver_number":44,"speed":85,"gear":2,"gear_switches":158,"drs":0,"lap_pos":0.1313,"engine_rpm":7796,"tyre_compound":[[5,2]],"start_pos":0,"points":37,"speed_traps":[268,227,234,281],"max_speed_traps":[270,227,235,281],"s1":32.414,"s2":32.885,"s3":26.159,"best_times":[32.414,32.671,26.1,91.458]},"V.BOTTAS":{"updated":0,"state":0,"lap":1,"lap_time":0,"position":6,"gap":10.458,"interval":0.507,"pits":0,"best_time":3,"driver_number":77,"speed":78,"gear":1,"gear_switches":141,"drs":0,"lap_pos":0.9644,"engine_rpm":8517,"tyre_compound":[[5,1]],"start_pos":0,"points":43,"speed_traps":[253,223,0,288],"max_speed_traps":[254,223,241,288],"s1":33.339,"s2":34.664,"s3":0,"best_times":[33.339,34.664,26.469,0]},"L.STROLL":{"updated":0,"state":0,"lap":2,"lap_time":93.732,"position":2,"gap":5.332,"interval":5.332,"pits":0,"best_time":65,"driver_number":18,"speed":267,"gear":7,"gear_switches":155,"drs":0,"lap_pos":0.0781,"engine_rpm":10740,"tyre_compound":[[5,2]],"start_pos":0,"points":6,"speed_traps":[270,219,239,284],"max_speed_traps":[270,219,239,285],"s1":32.726,"s2":34.133,"s3":26.873,"best_times":[32.726,33.98,26.715,93.732]},"S.PEREZ":{"updated":0,"state":0,"lap":1,"lap_time":0,"position":7,"gap":12.126,"interval":1.483,"pits":0,"best_time":3,"driver_number":11,"speed":235,"gear":6,"gear_switches":128,"drs":0,"lap_pos":0.9656,"engine_rpm":11161,"tyre_compound":[[5,1]],"start_pos":0,"points":16,"speed_traps":[250,225,0,288],"max_speed_traps":[250,225,236,288],"s1":33.236,"s2":35.302,"s3":0,"best_times":[33.236,35.302,27.046,0]},"S.VETTEL":{"updated":0,"state":0,"lap":2,"lap_time":94.777,"position":4,"gap":8.395,"interval":2.703,"pits":0,"best_time":67,"driver_number":5,"speed":280,"gear":7,"gear_switches":171,"drs":0,"lap_pos":0.0236,"engine_rpm":11325,"tyre_compound":[[5,1]],"start_pos":0,"points":1,"speed_traps":[266,220,235,283],"max_speed_traps":[266,224,237,283],"s1":33.098,"s2":34.57,"s3":27.109,"best_times":[33.098,34.57,26.719,94.777]},"C.LECLERC":{"updated":0,"state":0,"lap":1,"lap_time":0,"position":5,"gap":9.951,"interval":1.737,"pits":0,"best_time":3,"driver_number":16,"speed":79,"gear":2,"gear_switches":158,"drs":0,"lap_pos":0.9693,"engine_rpm":6930,"tyre_compound":[[5,1]],"start_pos":0,"points":18,"speed_traps":[264,221,0,281],"max_speed_traps":[264,221,237,281],"s1":33.58,"s2":34.542,"s3":0,"best_times":[33.58,34.542,26.862,0]},"M.VERSTAPPEN":{"updated":0,"state":0,"lap":2,"lap_time":93.264,"position":3,"gap":5.58,"interval":0.248,"pits":0,"best_time":67,"driver_number":33,"speed":269,"gear":8,"gear_switches":178,"drs":0,"lap_pos":0.0753,"engine_rpm":9520,"tyre_compound":[[5,2]],"start_pos":0,"points":15,"speed_traps":[267,224,239,290],"max_speed_traps":[267,224,239,285],"s1":32.617,"s2":34.111,"s3":26.536,"best_times":[32.617,34.111,26.521,93.264]},"L.NORRIS":{"updated":0,"state":0,"lap":1,"lap_time":0,"position":13,"gap":19.118,"interval":1.744,"pits":0,"best_time":3,"driver_number":4,"speed":123,"gear":3,"gear_switches":179,"drs":0,"lap_pos":0.8979,"engine_rpm":8187,"tyre_compound":[[5,1]],"start_pos":0,"points":26,"speed_traps":[241,215,0,288],"max_speed_traps":[241,218,236,288],"s1":34.088,"s2":35.444,"s3":0,"best_times":[34.088,35.444,27.783,0]},"C.SAINZ":{"updated":0,"state":0,"lap":1,"lap_time":0,"position":8,"gap":13.438,"interval":1.312,"pits":0,"best_time":3,"driver_number":55,"speed":203,"gear":5,"gear_switches":167,"drs":0,"lap_pos":0.9522,"engine_rpm":10564,"tyre_compound":[[5,1]],"start_pos":0,"points":13,"speed_traps":[248,216,0,287],"max_speed_traps":[248,219,237,287],"s1":33.19,"s2":35.607,"s3":0,"best_times":[33.19,35.607,26.96,0]},"P.GASLY":{"updated":0,"state":0,"lap":1,"lap_time":0,"position":12,"gap":17.374,"interval":0.823,"pits":0,"best_time":3,"driver_number":10,"speed":99,"gear":3,"gear_switches":161,"drs":0,"lap_pos":0.9166,"engine_rpm":7451,"tyre_compound":[[5,1]],"start_pos":0,"points":6,"speed_traps":[252,217,0,288],"max_speed_traps":[252,217,238,288],"s1":34.308,"s2":35.061,"s3":0,"best_times":[34.308,35.061,27.451,0]},"D.RICCIARDO":{"updated":0,"state":0,"lap":1,"lap_time":0,"position":9,"gap":15.12,"interval":1.682,"pits":0,"best_time":3,"driver_number":3,"speed":151,"gear":3,"gear_switches":159,"drs":0,"lap_pos":0.9349,"engine_rpm":10966,"tyre_compound":[[5,1]],"start_pos":0,"points":4,"speed_traps":[239,219,0,283],"max_speed_traps":[239,219,236,283],"s1":34.093,"s2":35.521,"s3":0,"best_times":[34.093,35.521,27.033,0]},"G.RUSSELL":{"updated":0,"state":0,"lap":1,"lap_time":0,"position":16,"gap":20.309,"interval":0.641,"pits":0,"best_time":3,"driver_number":63,"speed":179,"gear":4,"gear_switches":140,"drs":0,"lap_pos":0.8806,"engine_rpm":10206,"tyre_compound":[[5,1]],"start_pos":0,"points":0,"speed_traps":[226,217,0,289],"max_speed_traps":[226,217,237,289],"s1":34.686,"s2":35.873,"s3":0,"best_times":[34.686,35.873,27.906,0]},"A.ALBON":{"updated":0,"state":0,"lap":1,"lap_time":0,"position":11,"gap":16.551,"interval":0.8,"pits":0,"best_time":3,"driver_number":23,"speed":128,"gear":3,"gear_switches":147,"drs":0,"lap_pos":0.9213,"engine_rpm":9557,"tyre_compound":[[5,1]],"start_pos":0,"points":12,"speed_traps":[225,221,0,289],"max_speed_traps":[225,221,239,289],"s1":33.917,"s2":35.41,"s3":0,"best_times":[33.917,35.41,27.781,0]},"N.LATIFI":{"updated":0,"state":0,"lap":1,"lap_time":0,"position":10,"gap":15.751,"interval":0.792,"pits":0,"best_time":3,"driver_number":6,"speed":133,"gear":3,"gear_switches":147,"drs":0,"lap_pos":0.9281,"engine_rpm":10090,"tyre_compound":[[5,1]],"start_pos":0,"points":0,"speed_traps":[262,221,0,284],"max_speed_traps":[262,221,238,284],"s1":33.612,"s2":35.407,"s3":0,"best_times":[33.612,35.407,27.891,0]},"K.MAGNUSSEN":{"updated":0,"state":0,"lap":1,"lap_time":0,"position":18,"gap":28.074,"interval":6.357,"pits":0,"best_time":3,"driver_number":20,"speed":135,"gear":4,"gear_switches":164,"drs":0,"lap_pos":0.8251,"engine_rpm":9115,"tyre_compound":[[6,1]],"start_pos":0,"points":0,"speed_traps":[246,215,0,279],"max_speed_traps":[246,215,217,279],"s1":36.492,"s2":35.235,"s3":0,"best_times":[36.492,35.235,28.209,0]},"D.KVYAT":{"updated":0,"state":0,"lap":1,"lap_time":0,"position":20,"gap":42.64,"interval":11.928,"pits":1,"best_time":0,"driver_number":26,"speed":173,"gear":4,"gear_switches":120,"drs":0,"lap_pos":0.6494,"engine_rpm":10744,"tyre_compound":[[5,1],[9,0]],"start_pos":0,"points":1,"speed_traps":[221,0,0,0],"max_speed_traps":[221,217,0,251],"s1":57.053,"s2":0,"s3":0,"best_times":[57.053,37.939,30.7,0]},"R.GROSJEAN":{"updated":0,"state":0,"lap":1,"lap_time":0,"position":19,"gap":31.835,"interval":3.382,"pits":0,"best_time":3,"driver_number":8,"speed":117,"gear":3,"gear_switches":157,"drs":0,"lap_pos":0.7954,"engine_rpm":9001,"tyre_compound":[[5,1]],"start_pos":0,"points":0,"speed_traps":[237,215,0,284],"max_speed_traps":[237,215,231,284],"s1":38.015,"s2":35.652,"s3":0,"best_times":[38.015,35.652,28.053,0]},"A.GIOVINAZZI":{"updated":0,"state":0,"lap":1,"lap_time":0,"position":17,"gap":21.717,"interval":1.408,"pits":0,"best_time":3,"driver_number":99,"speed":130,"gear":2,"gear_switches":174,"drs":0,"lap_pos":0.8694,"engine_rpm":11468,"tyre_compound":[[5,1]],"start_pos":0,"points":2,"speed_traps":[238,216,0,289],"max_speed_traps":[238,216,237,289],"s1":34.209,"s2":36.574,"s3":0,"best_times":[34.209,36.574,28.395,0]},"K.RAIKKONEN":{"updated":0,"state":0,"lap":1,"lap_time":0,"position":15,"gap":19.668,"interval":0.557,"pits":0,"best_time":3,"driver_number":7,"speed":149,"gear":4,"gear_switches":154,"drs":0,"lap_pos":0.8833,"engine_rpm":9394,"tyre_compound":[[5,1]],"start_pos":0,"points":0,"speed_traps":[214,213,0,287],"max_speed_traps":[217,218,234,287],"s1":34.169,"s2":35.598,"s3":0,"best_times":[34.169,35.598,28.031,0]}}