{"version":9,"K.RAIKKONEN":{"updated":0,"state":0,"lap":63,"lap_time":68.934,"position":11,"gap":-1,"interval":4.563,"pits":1,"best_time":0,"driver_number":7,"speed":240,"gear":6,"gear_switches":2892,"drs":0,"lap_pos":0.9994,"engine_rpm":11172,"tyre_compound":[[10,44],[9,19]],"start_pos":16,"points":0,"speed_traps":[286,235,0,279],"max_speed_traps":[323,236,283,316],"s1":17.501,"s2":30.362,"s3":0,"best_times":[16.989,30.22,20.688,68.382]},"C.SAINZ":{"updated":0,"state":0,"lap":64,"lap_time":68.545,"position":9,"gap":65.617,"interval":3.305,"pits":1,"best_time":0,"driver_number":55,"speed":286,"gear":7,"gear_switches":2499,"drs":0,"lap_pos":0.5014,"engine_rpm":11107,"tyre_compound":[[9,32],[10,32]],"start_pos":3,"points":10,"speed_traps":[304,0,0,0],"max_speed_traps":[327,242,284,324],"s1":17.087,"s2":0,"s3":0,"best_times":[16.898,30.176,20.436,68.067]},"L.HAMILTON":{"updated":0,"state":0,"lap":65,"lap_time":69.083,"position":1,"gap":0,"interval":0,"pits":1,"best_time":0,"driver_number":44,"speed":263,"gear":7,"gear_switches":2293,"drs":0,"lap_pos":0.4297,"engine_rpm":10722,"tyre_compound":[[9,27],[10,38]],"start_pos":0,"points":12,"speed_traps":[306,0,0,0],"max_speed_traps":[313,241,283,299],"s1":16.902,"s2":0,"s3":0,"best_times":[16.888,29.972,20.516,67.651]},"M.VERSTAPPEN":{"updated":0,"state":0,"lap":65,"lap_time":68.532,"position":2,"gap":10.143,"interval":10.143,"pits":1,"best_time":0,"driver_number":33,"speed":301,"gear":8,"gear_switches":2638,"drs":0,"lap_pos":0.2999,"engine_rpm":10912,"tyre_compound":[[9,24],[10,41]],"start_pos":0,"points":0,"speed_traps":[288,238,278,285],"max_speed_traps":[309,239,285,308],"s1":17.424,"s2":30.401,"s3":20.707,"best_times":[17.02,30.002,20.52,67.81]},"V.BOTTAS":{"updated":0,"state":0,"lap":65,"lap_time":67.691,"position":3,"gap":10.361,"interval":0.26,"pits":1,"best_time":0,"driver_number":77,"speed":330,"gear":8,"gear_switches":2408,"drs":2,"lap_pos":0.2976,"engine_rpm":11843,"tyre_compound":[[9,34],[10,31]],"start_pos":0,"points":25,"speed_traps":[299,242,289,302],"max_speed_traps":[319,242,289,317],"s1":17.107,"s2":30.058,"s3":20.526,"best_times":[16.767,30.007,20.385,67.534]},"E.OCON":{"updated":0,"state":1,"lap":25,"lap_time":73.476,"position":18,"gap":0,"interval":0,"pits":1,"best_time":0,"driver_number":31,"speed":0,"gear":0,"gear_switches":1198,"drs":0,"lap_pos":0.0102,"engine_rpm":0,"tyre_compound":[[9,25]],"start_pos":0,"points":4,"speed_traps":[309,231,0,302],"max_speed_traps":[313,231,280,310],"s1":17.288,"s2":31.048,"s3":25.14,"best_times":[17.158,30.828,21.151,69.321]},"A.ALBON":{"updated":0,"state":0,"lap":64,"lap_time":67.519,"position":4,"gap":45.481,"interval":34.061,"pits":1,"best_time":0,"driver_number":23,"speed":223,"gear":5,"gear_switches":2421,"drs":0,"lap_pos":0.811,"engine_rpm":11046,"tyre_compound":[[9,35],[10,29]],"start_pos":0,"points":0,"speed_traps":[292,240,0,283],"max_speed_traps":[321,240,287,308],"s1":17.198,"s2":29.907,"s3":0,"best_times":[17.015,29.869,20.294,67.449]},"P.GASLY":{"updated":0,"state":0,"lap":63,"lap_time":68.405,"position":15,"gap":-1,"interval":21.236,"pits":2,"best_time":0,"driver_number":10,"speed":263,"gear":6,"gear_switches":2572,"drs":0,"lap_pos":0.6642,"engine_rpm":12028,"tyre_compound":[[9,24],[11,25],[9,14]],"start_pos":0,"points":6,"speed_traps":[286,0,0,288],"max_speed_traps":[325,235,285,320],"s1":17.564,"s2":0,"s3":0,"best_times":[16.81,30.049,20.673,68.226]},"D.RICCIARDO":{"updated":0,"state":0,"lap":64,"lap_time":67.993,"position":6,"gap":58.935,"interval":12.473,"pits":1,"best_time":0,"driver_number":3,"speed":159,"gear":3,"gear_switches":2681,"drs":0,"lap_pos":0.5714,"engine_rpm":11894,"tyre_compound":[[10,37],[9,27]],"start_pos":0,"points":0,"speed_traps":[311,0,0,287],"max_speed_traps":[323,239,282,317],"s1":17.038,"s2":0,"s3":0,"best_times":[17.015,30.118,20.599,67.98]},"L.NORRIS":{"updated":0,"state":0,"lap":64,"lap_time":67.286,"position":8,"gap":62.319,"interval":2.834,"pits":1,"best_time":128,"driver_number":4,"speed":152,"gear":5,"gear_switches":2553,"drs":0,"lap_pos":0.5418,"engine_rpm":9717,"tyre_compound":[[9,39],[10,25]],"start_pos":0,"points":16,"speed_traps":[295,0,0,293],"max_speed_traps":[326,240,286,318],"s1":17.183,"s2":0,"s3":0,"best_times":[16.983,29.893,20.243,67.286]},"S.VETTEL":{"updated":0,"state":1,"lap":1,"lap_time":0,"position":20,"gap":0,"interval":0,"pits":1,"best_time":2,"driver_number":5,"speed":0,"gear":8,"gear_switches":118,"drs":0,"lap_pos":0,"engine_rpm":0,"tyre_compound":[[10,1]],"start_pos":0,"points":1,"speed_traps":[293,174,0,245],"max_speed_traps":[293,174,0,245],"s1":0,"s2":39.412,"s3":38.926,"best_times":[0,39.412,38.926,0]},"G.RUSSELL":{"updated":0,"state":0,"lap":63,"lap_time":68.974,"position":16,"gap":-1,"interval":5.849,"pits":1,"best_time":0,"driver_number":63,"speed":101,"gear":3,"gear_switches":2349,"drs":0,"lap_pos":0.5611,"engine_rpm":7559,"tyre_compound":[[9,34],[10,29]],"start_pos":0,"points":0,"speed_traps":[240,0,0,308],"max_speed_traps":[324,238,286,318],"s1":17.665,"s2":0,"s3":0,"best_times":[16.841,30.437,20.769,68.601]},"L.STROLL":{"updated":0,"state":0,"lap":64,"lap_time":67.975,"position":7,"gap":59.485,"interval":0.55,"pits":1,"best_time":1,"driver_number":18,"speed":126,"gear":3,"gear_switches":2665,"drs":0,"lap_pos":0.5651,"engine_rpm":9587,"tyre_compound":[[9,33],[10,31]],"start_pos":0,"points":0,"speed_traps":[325,0,0,310],"max_speed_traps":[330,241,288,320],"s1":16.847,"s2":0,"s3":0,"best_times":[16.847,30.145,20.531,67.931]},"D.KVYAT":{"updated":0,"state":0,"lap":64,"lap_time":68.593,"position":10,"gap":-1,"interval":28.142,"pits":1,"best_time":0,"driver_number":26,"speed":293,"gear":7,"gear_switches":2441,"drs":0,"lap_pos":0.0068,"engine_rpm":11754,"tyre_compound":[[10,36],[11,28]],"start_pos":0,"points":0,"speed_traps":[292,226,274,288],"max_speed_traps":[321,229,280,314],"s1":17.465,"s2":30.47,"s3":20.658,"best_times":[16.993,30.339,20.519,68.378]},"C.LECLERC":{"updated":0,"state":1,"lap":4,"lap_time":92.548,"position":19,"gap":0,"interval":0,"pits":2,"best_time":1,"driver_number":16,"speed":0,"gear":0,"gear_switches":236,"drs":0,"lap_pos":0,"engine_rpm":0,"tyre_compound":[[9,1],[11,3]],"start_pos":0,"points":18,"speed_traps":[240,187,0,240],"max_speed_traps":[270,197,240,267],"s1":21.079,"s2":38.615,"s3":32.854,"best_times":[21.079,35.117,26.957,95.379]},"K.MAGNUSSEN":{"updated":0,"state":0,"lap":63,"lap_time":68.858,"position":14,"gap":-1,"interval":0.84,"pits":1,"best_time":0,"driver_number":20,"speed":183,"gear":5,"gear_switches":2577,"drs":1,"lap_pos":0.9994,"engine_rpm":9501,"tyre_compound":[[9,31],[10,32]],"start_pos":0,"points":0,"speed_traps":[318,231,0,312],"max_speed_traps":[322,236,286,318],"s1":16.987,"s2":31.019,"s3":0,"best_times":[16.87,30.364,20.698,68.327]},"S.PEREZ":{"updated":0,"state":0,"lap":64,"lap_time":67.59,"position":5,"gap":46.227,"interval":0.746,"pits":1,"best_time":0,"driver_number":11,"speed":196,"gear":5,"gear_switches":2543,"drs":0,"lap_pos":0.7985,"engine_rpm":10728,"tyre_compound":[[9,38],[10,26]],"start_pos":0,"points":8,"speed_traps":[310,239,0,308],"max_speed_traps":[336,241,290,322],"s1":16.879,"s2":30.03,"s3":0,"best_times":[16.761,29.781,20.283,67.396]},"N.LATIFI":{"updated":0,"state":0,"lap":63,"lap_time":70.284,"position":17,"gap":-1,"interval":6.803,"pits":1,"best_time":0,"driver_number":6,"speed":296,"gear":7,"gear_switches":2677,"drs":2,"lap_pos":0.4775,"engine_rpm":11827,"tyre_compound":[[10,32],[9,31]],"start_pos":0,"points":0,"speed_traps":[308,0,0,0],"max_speed_traps":[315,238,283,317],"s1":18.721,"s2":0,"s3":0,"best_times":[17.154,30.556,20.839,69.219]},"A.GIOVINAZZI":{"updated":0,"state":0,"lap":63,"lap_time":68.832,"position":12,"gap":-1,"interval":1.443,"pits":1,"best_time":0,"driver_number":99,"speed":210,"gear":5,"gear_switches":2683,"drs":0,"lap_pos":0.9994,"engine_rpm":11504,"tyre_compound":[[10,39],[9,24]],"start_pos":0,"points":2,"speed_traps":[299,239,0,288],"max_speed_traps":[325,242,288,323],"s1":17.325,"s2":30.76,"s3":0,"best_times":[16.929,30.404,20.675,68.512]},"R.GROSJEAN":{"updated":0,"state":0,"lap":63,"lap_time":68.888,"position":13,"gap":-1,"interval":0.637,"pits":1,"best_time":1,"driver_number":8,"speed":173,"gear":5,"gear_switches":2519,"drs":1,"lap_pos":0.9994,"engine_rpm":9463,"tyre_compound":[[9,37],[10,26]],"start_pos":0,"points":0,"speed_traps":[318,235,0,305],"max_speed_traps":[321,236,283,317],"s1":16.989,"s2":31.122,"s3":0,"best_times":[16.989,30.319,20.596,68.342]}}