{"version":9,"C.SAINZ":{"updated":0,"state":0,"lap":33,"lap_time":112.257,"position":3,"gap":21.185,"interval":8.974,"pits":2,"best_time":0,"driver_number":55,"speed":278,"gear":7,"gear_switches":1713,"drs":0,"lap_pos":0.1215,"engine_rpm":11278,"tyre_compound":[[9,13],[10,14],[11,8]],"start_pos":1,"points":156,"speed_traps":[310,188,210,312],"max_speed_traps":[336,195,219,312],"s1":32.275,"s2":49.498,"s3":30.484,"best_times":[32.129,49.225,30.387,111.977]},"S.PEREZ":{"updated":0,"state":0,"lap":33,"lap_time":111.885,"position":2,"gap":12.257,"interval":12.257,"pits":2,"best_time":0,"driver_number":11,"speed":315,"gear":8,"gear_switches":1586,"drs":0,"lap_pos":0.1917,"engine_rpm":11180,"tyre_compound":[[10,14],[10,13],[11,6]],"start_pos":2,"points":173,"speed_traps":[321,187,214,313],"max_speed_traps":[337,194,214,314],"s1":31.978,"s2":49.471,"s3":30.436,"best_times":[31.853,48.661,30.107,110.764]},"F.ALONSO":{"updated":0,"state":0,"lap":32,"lap_time":113.372,"position":7,"gap":58.352,"interval":9.643,"pits":2,"best_time":2,"driver_number":14,"speed":294,"gear":7,"gear_switches":1769,"drs":0,"lap_pos":0.8082,"engine_rpm":11288,"tyre_compound":[[10,11],[10,14],[11,7]],"start_pos":3,"points":41,"speed_traps":[305,185,0,311],"max_speed_traps":[339,193,215,317],"s1":32.48,"s2":50.082,"s3":0,"best_times":[31.753,50.082,30.341,112.981]},"L.HAMILTON":{"updated":0,"state":1,"lap":0,"lap_time":0,"position":20,"gap":0,"interval":0,"pits":0,"best_time":2,"driver_number":44,"speed":9,"gear":0,"gear_switches":250,"drs":0,"lap_pos":0.8579,"engine_rpm":0,"tyre_compound":[[10,0]],"start_pos":4,"points":146,"speed_traps":[324,146,0,306],"max_speed_traps":[324,146,0,306],"s1":0,"s2":56.359,"s3":0,"best_times":[0,56.359,0,0]},"G.RUSSELL":{"updated":0,"state":0,"lap":33,"lap_time":111.119,"position":4,"gap":25.001,"interval":4.037,"pits":2,"best_time":0,"driver_number":63,"speed":182,"gear":4,"gear_switches":1938,"drs":0,"lap_pos":0.0895,"engine_rpm":11355,"tyre_compound":[[10,13],[10,16],[11,4]],"start_pos":5,"points":158,"speed_traps":[307,190,214,308],"max_speed_traps":[322,196,217,312],"s1":32.282,"s2":48.526,"s3":30.311,"best_times":[32.194,48.304,30.236,110.793]},"A.ALBON":{"updated":0,"state":0,"lap":32,"lap_time":113.935,"position":10,"gap":75.374,"interval":6.536,"pits":2,"best_time":0,"driver_number":23,"speed":167,"gear":4,"gear_switches":1794,"drs":0,"lap_pos":0.6441,"engine_rpm":10339,"tyre_compound":[[10,10],[11,16],[10,6]],"start_pos":6,"points":3,"speed_traps":[314,0,0,312],"max_speed_traps":[339,193,216,313],"s1":32.072,"s2":0,"s3":0,"best_times":[31.824,49.918,30.252,113.055]},"D.RICCIARDO":{"updated":0,"state":0,"lap":32,"lap_time":119.059,"position":15,"gap":81.749,"interval":0.416,"pits":2,"best_time":0,"driver_number":3,"speed":292,"gear":7,"gear_switches":1911,"drs":0,"lap_pos":0.5762,"engine_rpm":11628,"tyre_compound":[[10,12],[11,20],[10,0]],"start_pos":7,"points":19,"speed_traps":[337,0,0,311],"max_speed_traps":[337,190,214,312],"s1":46.266,"s2":0,"s3":0,"best_times":[31.932,50.441,30.569,114.129]},"P.GASLY":{"updated":0,"state":0,"lap":32,"lap_time":113.584,"position":8,"gap":65.469,"interval":7.21,"pits":2,"best_time":0,"driver_number":10,"speed":221,"gear":5,"gear_switches":1635,"drs":0,"lap_pos":0.7292,"engine_rpm":10483,"tyre_compound":[[10,10],[11,12],[10,10]],"start_pos":8,"points":16,"speed_traps":[315,185,0,310],"max_speed_traps":[345,191,213,315],"s1":32.255,"s2":50.683,"s3":0,"best_times":[31.959,50.506,30.297,113.002]},"L.STROLL":{"updated":0,"state":0,"lap":32,"lap_time":114.026,"position":11,"gap":75.604,"interval":0.553,"pits":2,"best_time":0,"driver_number":18,"speed":156,"gear":4,"gear_switches":1850,"drs":0,"lap_pos":0.6404,"engine_rpm":9903,"tyre_compound":[[10,16],[10,12],[11,6]],"start_pos":9,"points":4,"speed_traps":[323,0,0,314],"max_speed_traps":[338,190,214,314],"s1":31.978,"s2":0,"s3":0,"best_times":[31.797,50.221,30.34,112.88]},"S.VETTEL":{"updated":0,"state":0,"lap":32,"lap_time":114.518,"position":6,"gap":48.793,"interval":8.152,"pits":1,"best_time":0,"driver_number":5,"speed":308,"gear":8,"gear_switches":1900,"drs":0,"lap_pos":0.9291,"engine_rpm":11349,"tyre_compound":[[10,15],[11,18]],"start_pos":10,"points":16,"speed_traps":[309,184,0,309],"max_speed_traps":[335,190,216,312],"s1":32.566,"s2":51.565,"s3":0,"best_times":[31.995,50.797,30.493,113.525]},"N.LATIFI":{"updated":0,"state":0,"lap":32,"lap_time":116.002,"position":17,"gap":91.213,"interval":5.284,"pits":2,"best_time":0,"driver_number":6,"speed":248,"gear":6,"gear_switches":1788,"drs":0,"lap_pos":0.4665,"engine_rpm":10490,"tyre_compound":[[10,3],[10,13],[11,17]],"start_pos":11,"points":0,"speed_traps":[313,0,0,309],"max_speed_traps":[344,189,212,312],"s1":32.6,"s2":0,"s3":0,"best_times":[32.044,51.502,30.682,114.803]},"K.MAGNUSSEN":{"updated":0,"state":0,"lap":32,"lap_time":114.235,"position":16,"gap":86.036,"interval":4.527,"pits":2,"best_time":0,"driver_number":20,"speed":239,"gear":7,"gear_switches":1691,"drs":0,"lap_pos":0.5293,"engine_rpm":9700,"tyre_compound":[[10,11],[11,16],[10,5]],"start_pos":12,"points":22,"speed_traps":[313,0,0,310],"max_speed_traps":[327,193,214,313],"s1":32.301,"s2":0,"s3":0,"best_times":[32.043,49.45,30.656,113.332]},"V.BOTTAS":{"updated":0,"state":1,"lap":1,"lap_time":0,"position":19,"gap":0,"interval":0,"pits":0,"best_time":1,"driver_number":77,"speed":0,"gear":0,"gear_switches":344,"drs":0,"lap_pos":0.3414,"engine_rpm":0,"tyre_compound":[[9,1]],"start_pos":13,"points":46,"speed_traps":[310,0,0,303],"max_speed_traps":[328,182,213,303],"s1":32.5,"s2":0,"s3":0,"best_times":[32.5,55.363,32.345,0]},"M.VERSTAPPEN":{"updated":0,"state":0,"lap":33,"lap_time":111.144,"position":1,"gap":0,"interval":0,"pits":2,"best_time":0,"driver_number":1,"speed":145,"gear":4,"gear_switches":1782,"drs":0,"lap_pos":0.2987,"engine_rpm":8531,"tyre_compound":[[9,15],[10,15],[10,3]],"start_pos":14,"points":258,"speed_traps":[319,0,0,312],"max_speed_traps":[342,199,217,313],"s1":31.831,"s2":0,"s3":0,"best_times":[31.597,47.81,29.864,109.354]},"C.LECLERC":{"updated":0,"state":0,"lap":32,"lap_time":111.872,"position":5,"gap":40.596,"interval":15.498,"pits":2,"best_time":0,"driver_number":16,"speed":63,"gear":2,"gear_switches":1818,"drs":0,"lap_pos":0.9937,"engine_rpm":5950,"tyre_compound":[[9,3],[10,22],[10,7]],"start_pos":15,"points":178,"speed_traps":[309,188,0,311],"max_speed_traps":[339,194,215,316],"s1":32.125,"s2":49.395,"s3":0,"best_times":[31.824,49.201,30.464,111.677]},"E.OCON":{"updated":0,"state":0,"lap":32,"lap_time":118.692,"position":9,"gap":68.892,"interval":3.588,"pits":2,"best_time":0,"driver_number":31,"speed":140,"gear":4,"gear_switches":1688,"drs":0,"lap_pos":0.7022,"engine_rpm":8279,"tyre_compound":[[10,12],[11,20],[10,0]],"start_pos":16,"points":58,"speed_traps":[310,0,0,306],"max_speed_traps":[347,193,212,316],"s1":46.695,"s2":0,"s3":0,"best_times":[31.716,50.206,30.346,113.488]},"L.NORRIS":{"updated":0,"state":0,"lap":32,"lap_time":112.418,"position":12,"gap":76.233,"interval":0.629,"pits":2,"best_time":0,"driver_number":4,"speed":135,"gear":4,"gear_switches":1836,"drs":0,"lap_pos":0.6357,"engine_rpm":8715,"tyre_compound":[[10,13],[11,16],[10,3]],"start_pos":17,"points":76,"speed_traps":[318,0,0,316],"max_speed_traps":[330,192,218,316],"s1":31.761,"s2":0,"s3":0,"best_times":[31.543,50.067,30.068,111.678]},"G.ZHOU":{"updated":0,"state":0,"lap":32,"lap_time":112.375,"position":13,"gap":77.436,"interval":1.203,"pits":2,"best_time":0,"driver_number":24,"speed":155,"gear":5,"gear_switches":1711,"drs":0,"lap_pos":0.6269,"engine_rpm":7991,"tyre_compound":[[10,14],[10,14],[9,4]],"start_pos":18,"points":5,"speed_traps":[323,0,0,314],"max_speed_traps":[344,193,214,317],"s1":31.837,"s2":0,"s3":0,"best_times":[31.709,50.03,30.312,112.317]},"M.SCHUMACHER":{"updated":0,"state":0,"lap":32,"lap_time":112.212,"position":18,"gap":97.022,"interval":6.351,"pits":2,"best_time":64,"driver_number":47,"speed":149,"gear":3,"gear_switches":1729,"drs":0,"lap_pos":0.4116,"engine_rpm":11779,"tyre_compound":[[10,14],[11,16],[10,2]],"start_pos":19,"points":12,"speed_traps":[312,0,0,307],"max_speed_traps":[334,191,213,310],"s1":32.195,"s2":0,"s3":0,"best_times":[32.142,49.415,30.655,113.911]},"Y.TSUNODA":{"updated":0,"state":0,"lap":32,"lap_time":112.436,"position":14,"gap":81.333,"interval":3.969,"pits":2,"best_time":65,"driver_number":22,"speed":288,"gear":7,"gear_switches":1623,"drs":0,"lap_pos":0.5804,"engine_rpm":11434,"tyre_compound":[[11,18],[10,12],[10,2]],"start_pos":20,"points":11,"speed_traps":[321,0,0,312],"max_speed_traps":[341,194,213,316],"s1":31.88,"s2":0,"s3":0,"best_times":[31.88,50.221,30.258,112.436]}}